ih2torrent.py
version.py
win_ih2torrent-0.2.0.dist-info/LICENSE.txt
win_ih2torrent-0.2.0.dist-info/METADATA
win_ih2torrent-0.2.0.dist-info/WHEEL
win_ih2torrent-0.2.0.dist-info/entry_points.txt
win_ih2torrent-0.2.0.dist-info/top_level.txt
win_ih2torrent-0.2.0.dist-info/RECORD
