Metadata-Version: 2.1
Name: win-ih2torrent
Version: 0.2.0
Summary: Convert a torrent infohash or magnet URI to a .torrent file using DHT and metadata protocol. Asyncio based for Windows devices.
Home-page: https://github.com/Mr-Developer-X/win_ih2torrent
Download-URL: https://github.com/Mr-Developer-X/win_ih2torrent/tarball/0.2.0
Author: Mr Developer X
Author-email: 139059229+Mr-Developer-X@users.noreply.github.com
License: GPL
Keywords: bittorrent,torrent,infohash,magnet,dht,metadata,metainfo,asyncio
Classifier: Programming Language :: Python :: 3
License-File: LICENSE.txt
Requires-Dist: aiodns (==3.0.0)
Requires-Dist: bencodepy (==0.9.5)
